jhrtools/__init__.py
jhrtools/data_source.py
jhrtools/rtdb.py
jhrtools/rule_base.py
jhrtools/tools.py
jhrtools-1.2.1.dist-info/METADATA
jhrtools-1.2.1.dist-info/WHEEL
jhrtools-1.2.1.dist-info/top_level.txt
jhrtools-1.2.1.dist-info/RECORD
