Metadata-Version: 2.1
Name: jhrtools
Version: 1.2.1
Summary: jet database tools
Home-page: UNKNOWN
Author: Haoran Ji
Author-email: 944816903@qq.com
License: MIT
Platform: UNKNOWN
Requires-Python: >=3.8
Requires-Dist: typeguard (==2.13.3)
Requires-Dist: pandas (==1.4.1)
Requires-Dist: pathos (==0.2.8)
Requires-Dist: requests (==2.27.1)
Requires-Dist: simplejson (==3.17.6)
Requires-Dist: SQLAlchemy (==1.4.32)
Requires-Dist: pymysql (==1.0.2)
Requires-Dist: tqdm (==4.63.0)
Requires-Dist: netifaces (==0.11.0)
